.gitignore
LICENSE.txt
README.md
README.rst
plover_system_switcher.py
setup.cfg
setup.py
plover_system_switcher.egg-info/PKG-INFO
plover_system_switcher.egg-info/SOURCES.txt
plover_system_switcher.egg-info/dependency_links.txt
plover_system_switcher.egg-info/entry_points.txt
plover_system_switcher.egg-info/requires.txt
plover_system_switcher.egg-info/top_level.txt
plover_system_switcher.egg-info/zip-safe